setup.py
statzlogger.py
statzlogger.egg-info/PKG-INFO
statzlogger.egg-info/SOURCES.txt
statzlogger.egg-info/dependency_links.txt
statzlogger.egg-info/requires.txt
statzlogger.egg-info/top_level.txt