Metadata-Version: 1.0
Name: statzlogger
Version: 0.1.0
Summary: statzlogger logs statz
Home-page: http://packages.python.org/statzlogger
Author: Will Maier
Author-email: willmaier@ml1.net
License: UNKNOWN
Keywords: logging statistics sawzall szl
Platform: UNKNOWN
Classifier: Development Status :: 3 - Alpha
Classifier: Intended Audience :: Developers
Classifier: License :: OSI Approved :: BSD License
Classifier: License :: OSI Approved :: MIT License
Classifier: Natural Language :: English
Classifier: Programming Language :: Python
Classifier: Topic :: System :: Logging
